ratelimiter/__init__.py
ratelimiter/_async.py
ratelimiter/_sync.py
pratelimiter-1.2.1.dist-info/LICENSE
pratelimiter-1.2.1.dist-info/METADATA
pratelimiter-1.2.1.dist-info/WHEEL
pratelimiter-1.2.1.dist-info/top_level.txt
pratelimiter-1.2.1.dist-info/RECORD
