Metadata-Version: 2.1
Name: pratelimiter
Version: 1.2.1
Summary: Simple python rate limiting object
Home-page: https://github.com/tuyenpthust/pratelimiter
Author: Tuyen Phan
Author-email: ruoitrau95@gmail.com
License: Apache
Classifier: Development Status :: 5 - Production/Stable
Classifier: License :: OSI Approved :: Apache Software License
License-File: LICENSE
Provides-Extra: test
Requires-Dist: pytest >=3.0 ; extra == 'test'
Requires-Dist: pytest-asyncio ; (python_version>="3.5") and extra == 'test'
